isoweek.py
isoweek-1.3.2.dist-info/DESCRIPTION.rst
isoweek-1.3.2.dist-info/METADATA
isoweek-1.3.2.dist-info/RECORD
isoweek-1.3.2.dist-info/WHEEL
isoweek-1.3.2.dist-info/metadata.json
isoweek-1.3.2.dist-info/top_level.txt
