Metadata-Version: 2.0
Name: isoweek
Version: 1.3.2
Summary: Objects representing a week
Home-page: http://github.com/gisle/isoweek
Author: Gisle Aas
Author-email: gisle@aas.no
License: BSD
Platform: UNKNOWN
Classifier: Development Status :: 5 - Production/Stable
Classifier: Intended Audience :: Developers
Classifier: License :: OSI Approved :: BSD License
Classifier: Operating System :: OS Independent
Classifier: Programming Language :: Python
Classifier: Programming Language :: Python :: 2.6
Classifier: Programming Language :: Python :: 2.7
Classifier: Programming Language :: Python :: 3
Classifier: Topic :: Software Development :: Libraries :: Python Modules
